odoo/addons/easy_my_coop_loan_account/README.rst
odoo/addons/easy_my_coop_loan_account/__init__.py
odoo/addons/easy_my_coop_loan_account/__manifest__.py
odoo/addons/easy_my_coop_loan_account/data/emc_loan_account_data.xml
odoo/addons/easy_my_coop_loan_account/demo/emc_loan_account_demo.xml
odoo/addons/easy_my_coop_loan_account/i18n/easy_my_coop_loan_account.pot
odoo/addons/easy_my_coop_loan_account/models/__init__.py
odoo/addons/easy_my_coop_loan_account/models/account_fiscal_year.py
odoo/addons/easy_my_coop_loan_account/models/account_move.py
odoo/addons/easy_my_coop_loan_account/models/company.py
odoo/addons/easy_my_coop_loan_account/models/interest_line.py
odoo/addons/easy_my_coop_loan_account/models/loan_issue_line.py
odoo/addons/easy_my_coop_loan_account/readme/CONTRIBUTORS.rst
odoo/addons/easy_my_coop_loan_account/readme/DESCRIPTION.rst
odoo/addons/easy_my_coop_loan_account/static/description/index.html
odoo/addons/easy_my_coop_loan_account/views/interest_line_view.xml
odoo/addons/easy_my_coop_loan_account/views/loan_issue_line_view.xml
odoo/addons/easy_my_coop_loan_account/views/res_company_view.xml
odoo/addons/easy_my_coop_loan_account/wizard/__init__.py
odoo/addons/easy_my_coop_loan_account/wizard/end_of_year_operation.py
odoo/addons/easy_my_coop_loan_account/wizard/end_of_year_operation.xml
odoo12_addon_easy_my_coop_loan_account-12.0.1.0.0.99.dev8.dist-info/METADATA
odoo12_addon_easy_my_coop_loan_account-12.0.1.0.0.99.dev8.dist-info/WHEEL
odoo12_addon_easy_my_coop_loan_account-12.0.1.0.0.99.dev8.dist-info/top_level.txt
odoo12_addon_easy_my_coop_loan_account-12.0.1.0.0.99.dev8.dist-info/RECORD
